{
    "omega-ruby-alpha-sapphire": [
        "Scratch learnt at level 1",
        "Foresight learnt at level 1",
        "Defense-curl learnt at level 4",
        "Quick-attack learnt at level 7",
        "Fury-swipes learnt at level 13",
        "Helping-hand learnt at level 16",
        "Follow-me learnt at level 19",
        "Slam learnt at level 25",
        "Rest learnt at level 28",
        "Sucker-punch learnt at level 31",
        "Amnesia learnt at level 36",
        "Baton-pass learnt at level 39",
        "Me-first learnt at level 42",
        "Hyper-voice learnt at level 47"
    ],
    "black-2-white-2": [
        "Scratch learnt at level 1",
        "Foresight learnt at level 1",
        "Defense-curl learnt at level 4",
        "Quick-attack learnt at level 7",
        "Fury-swipes learnt at level 13",
        "Helping-hand learnt at level 16",
        "Follow-me learnt at level 19",
        "Slam learnt at level 25",
        "Rest learnt at level 28",
        "Sucker-punch learnt at level 31",
        "Amnesia learnt at level 36",
        "Baton-pass learnt at level 39",
        "Me-first learnt at level 42",
        "Hyper-voice learnt at level 47"
    ],
    "platinum": [
        "Scratch learnt at level 1",
        "Foresight learnt at level 1",
        "Defense-curl learnt at level 4",
        "Quick-attack learnt at level 7",
        "Fury-swipes learnt at level 13",
        "Helping-hand learnt at level 16",
        "Follow-me learnt at level 19",
        "Slam learnt at level 25",
        "Rest learnt at level 28",
        "Sucker-punch learnt at level 31",
        "Amnesia learnt at level 36",
        "Baton-pass learnt at level 39",
        "Me-first learnt at level 42",
        "Hyper-voice learnt at level 47"
    ],
    "emerald": [
        "Scratch learnt at level 1",
        "Defense-curl learnt at level 4",
        "Quick-attack learnt at level 7",
        "Fury-swipes learnt at level 12",
        "Helping-hand learnt at level 17",
        "Slam learnt at level 24",
        "Follow-me learnt at level 31",
        "Rest learnt at level 40",
        "Amnesia learnt at level 49"
    ],
    "crystal": [
        "Tackle learnt at level 1",
        "Defense-curl learnt at level 5",
        "Quick-attack learnt at level 11",
        "Fury-swipes learnt at level 17",
        "Slam learnt at level 25",
        "Rest learnt at level 33",
        "Amnesia learnt at level 41"
    ],
    "heartgold-soulsilver": [
        "Scratch learnt at level 1",
        "Foresight learnt at level 1",
        "Defense-curl learnt at level 4",
        "Quick-attack learnt at level 7",
        "Fury-swipes learnt at level 13",
        "Helping-hand learnt at level 16",
        "Follow-me learnt at level 19",
        "Slam learnt at level 25",
        "Rest learnt at level 28",
        "Sucker-punch learnt at level 31",
        "Amnesia learnt at level 36",
        "Baton-pass learnt at level 39",
        "Me-first learnt at level 42",
        "Hyper-voice learnt at level 47"
    ],
    "gold-silver": [
        "Tackle learnt at level 1",
        "Defense-curl learnt at level 5",
        "Quick-attack learnt at level 11",
        "Fury-swipes learnt at level 17",
        "Slam learnt at level 25",
        "Rest learnt at level 33",
        "Amnesia learnt at level 41"
    ],
    "sun-moon": [
        "Scratch learnt at level 1",
        "Foresight learnt at level 1",
        "Defense-curl learnt at level 4",
        "Quick-attack learnt at level 7",
        "Fury-swipes learnt at level 13",
        "Helping-hand learnt at level 16",
        "Follow-me learnt at level 19",
        "Slam learnt at level 25",
        "Rest learnt at level 28",
        "Sucker-punch learnt at level 31",
        "Amnesia learnt at level 36",
        "Baton-pass learnt at level 39",
        "Me-first learnt at level 42",
        "Hyper-voice learnt at level 47"
    ],
    "x-y": [
        "Scratch learnt at level 1",
        "Foresight learnt at level 1",
        "Defense-curl learnt at level 4",
        "Quick-attack learnt at level 7",
        "Fury-swipes learnt at level 13",
        "Helping-hand learnt at level 16",
        "Follow-me learnt at level 19",
        "Slam learnt at level 25",
        "Rest learnt at level 28",
        "Sucker-punch learnt at level 31",
        "Amnesia learnt at level 36",
        "Baton-pass learnt at level 39",
        "Me-first learnt at level 42",
        "Hyper-voice learnt at level 47"
    ],
    "xd": [
        "Scratch learnt at level 1",
        "Defense-curl learnt at level 4",
        "Quick-attack learnt at level 7",
        "Fury-swipes learnt at level 12",
        "Helping-hand learnt at level 17",
        "Slam learnt at level 24",
        "Follow-me learnt at level 31",
        "Rest learnt at level 40",
        "Amnesia learnt at level 49"
    ],
    "ultra-sun-ultra-moon": [
        "Scratch learnt at level 1",
        "Foresight learnt at level 1",
        "Defense-curl learnt at level 4",
        "Quick-attack learnt at level 7",
        "Fury-swipes learnt at level 13",
        "Helping-hand learnt at level 16",
        "Follow-me learnt at level 19",
        "Slam learnt at level 25",
        "Rest learnt at level 28",
        "Sucker-punch learnt at level 31",
        "Amnesia learnt at level 36",
        "Baton-pass learnt at level 39",
        "Me-first learnt at level 42",
        "Hyper-voice learnt at level 47"
    ],
    "colosseum": [
        "Scratch learnt at level 1",
        "Defense-curl learnt at level 4",
        "Quick-attack learnt at level 7",
        "Fury-swipes learnt at level 12",
        "Helping-hand learnt at level 17",
        "Slam learnt at level 24",
        "Follow-me learnt at level 31",
        "Rest learnt at level 40",
        "Amnesia learnt at level 49"
    ],
    "black-white": [
        "Scratch learnt at level 1",
        "Foresight learnt at level 1",
        "Defense-curl learnt at level 4",
        "Quick-attack learnt at level 7",
        "Fury-swipes learnt at level 13",
        "Helping-hand learnt at level 16",
        "Follow-me learnt at level 19",
        "Slam learnt at level 25",
        "Rest learnt at level 28",
        "Sucker-punch learnt at level 31",
        "Amnesia learnt at level 36",
        "Baton-pass learnt at level 39",
        "Me-first learnt at level 42",
        "Hyper-voice learnt at level 47"
    ],
    "diamond-pearl": [
        "Scratch learnt at level 1",
        "Foresight learnt at level 1",
        "Defense-curl learnt at level 4",
        "Quick-attack learnt at level 7",
        "Fury-swipes learnt at level 13",
        "Helping-hand learnt at level 16",
        "Follow-me learnt at level 19",
        "Slam learnt at level 25",
        "Rest learnt at level 28",
        "Sucker-punch learnt at level 31",
        "Amnesia learnt at level 36",
        "Baton-pass learnt at level 39",
        "Me-first learnt at level 42",
        "Hyper-voice learnt at level 47"
    ],
    "firered-leafgreen": [
        "Scratch learnt at level 1",
        "Defense-curl learnt at level 4",
        "Quick-attack learnt at level 7",
        "Fury-swipes learnt at level 12",
        "Helping-hand learnt at level 17",
        "Slam learnt at level 24",
        "Follow-me learnt at level 31",
        "Rest learnt at level 40",
        "Amnesia learnt at level 49"
    ],
    "ruby-sapphire": [
        "Scratch learnt at level 1",
        "Defense-curl learnt at level 4",
        "Quick-attack learnt at level 7",
        "Fury-swipes learnt at level 12",
        "Helping-hand learnt at level 17",
        "Slam learnt at level 24",
        "Follow-me learnt at level 31",
        "Rest learnt at level 40",
        "Amnesia learnt at level 49"
    ]
}