{
    "firered-leafgreen": [
        "Scratch learnt at level 1",
        "Leer learnt at level 1",
        "Lick learnt at level 1",
        "Fury-swipes learnt at level 1",
        "Lick learnt at level 7",
        "Fury-swipes learnt at level 13",
        "Fake-tears learnt at level 19",
        "Feint-attack learnt at level 25",
        "Rest learnt at level 31",
        "Slash learnt at level 37",
        "Snore learnt at level 43",
        "Thrash learnt at level 49"
    ],
    "emerald": [
        "Scratch learnt at level 1",
        "Leer learnt at level 1",
        "Lick learnt at level 1",
        "Fury-swipes learnt at level 1",
        "Lick learnt at level 7",
        "Fury-swipes learnt at level 13",
        "Fake-tears learnt at level 19",
        "Feint-attack learnt at level 25",
        "Rest learnt at level 31",
        "Slash learnt at level 37",
        "Snore learnt at level 43",
        "Thrash learnt at level 49"
    ],
    "heartgold-soulsilver": [
        "Scratch learnt at level 1",
        "Leer learnt at level 1",
        "Lick learnt at level 1",
        "Fake-tears learnt at level 1",
        "Covet learnt at level 1",
        "Fury-swipes learnt at level 8",
        "Feint-attack learnt at level 15",
        "Sweet-scent learnt at level 22",
        "Slash learnt at level 29",
        "Scary-face learnt at level 38",
        "Rest learnt at level 47",
        "Snore learnt at level 49",
        "Thrash learnt at level 58",
        "Hammer-arm learnt at level 67"
    ],
    "platinum": [
        "Scratch learnt at level 1",
        "Leer learnt at level 1",
        "Lick learnt at level 1",
        "Fake-tears learnt at level 1",
        "Covet learnt at level 1",
        "Fury-swipes learnt at level 8",
        "Feint-attack learnt at level 15",
        "Sweet-scent learnt at level 22",
        "Slash learnt at level 29",
        "Scary-face learnt at level 38",
        "Rest learnt at level 47",
        "Snore learnt at level 49",
        "Thrash learnt at level 58",
        "Hammer-arm learnt at level 67"
    ],
    "omega-ruby-alpha-sapphire": [
        "Scratch learnt at level 1",
        "Leer learnt at level 1",
        "Lick learnt at level 1",
        "Fake-tears learnt at level 1",
        "Covet learnt at level 1",
        "Hammer-arm learnt at level 1",
        "Fury-swipes learnt at level 8",
        "Feint-attack learnt at level 15",
        "Sweet-scent learnt at level 22",
        "Play-nice learnt at level 25",
        "Slash learnt at level 29",
        "Scary-face learnt at level 38",
        "Rest learnt at level 47",
        "Snore learnt at level 49",
        "Thrash learnt at level 58",
        "Hammer-arm learnt at level 67"
    ],
    "black-2-white-2": [
        "Scratch learnt at level 1",
        "Leer learnt at level 1",
        "Lick learnt at level 1",
        "Fake-tears learnt at level 1",
        "Covet learnt at level 1",
        "Fury-swipes learnt at level 8",
        "Feint-attack learnt at level 15",
        "Sweet-scent learnt at level 22",
        "Slash learnt at level 29",
        "Scary-face learnt at level 38",
        "Rest learnt at level 47",
        "Snore learnt at level 49",
        "Thrash learnt at level 58",
        "Hammer-arm learnt at level 67"
    ],
    "crystal": [
        "Scratch learnt at level 1",
        "Leer learnt at level 1",
        "Lick learnt at level 1",
        "Fury-swipes learnt at level 1",
        "Lick learnt at level 8",
        "Fury-swipes learnt at level 15",
        "Feint-attack learnt at level 22",
        "Rest learnt at level 29",
        "Slash learnt at level 39",
        "Snore learnt at level 49",
        "Thrash learnt at level 59"
    ],
    "gold-silver": [
        "Scratch learnt at level 1",
        "Leer learnt at level 1",
        "Lick learnt at level 1",
        "Fury-swipes learnt at level 1",
        "Lick learnt at level 8",
        "Fury-swipes learnt at level 15",
        "Feint-attack learnt at level 22",
        "Rest learnt at level 29",
        "Slash learnt at level 39",
        "Snore learnt at level 49",
        "Thrash learnt at level 59"
    ],
    "xd": [
        "Scratch learnt at level 1",
        "Leer learnt at level 1",
        "Lick learnt at level 1",
        "Fury-swipes learnt at level 1",
        "Lick learnt at level 7",
        "Fury-swipes learnt at level 13",
        "Fake-tears learnt at level 19",
        "Feint-attack learnt at level 25",
        "Rest learnt at level 31",
        "Slash learnt at level 37",
        "Snore learnt at level 43",
        "Thrash learnt at level 49"
    ],
    "colosseum": [
        "Scratch learnt at level 1",
        "Leer learnt at level 1",
        "Lick learnt at level 1",
        "Fury-swipes learnt at level 1",
        "Lick learnt at level 7",
        "Fury-swipes learnt at level 13",
        "Fake-tears learnt at level 19",
        "Feint-attack learnt at level 25",
        "Rest learnt at level 31",
        "Slash learnt at level 37",
        "Snore learnt at level 43",
        "Thrash learnt at level 49"
    ],
    "black-white": [
        "Scratch learnt at level 1",
        "Leer learnt at level 1",
        "Lick learnt at level 1",
        "Fake-tears learnt at level 1",
        "Covet learnt at level 1",
        "Fury-swipes learnt at level 8",
        "Feint-attack learnt at level 15",
        "Sweet-scent learnt at level 22",
        "Slash learnt at level 29",
        "Scary-face learnt at level 38",
        "Rest learnt at level 47",
        "Snore learnt at level 49",
        "Thrash learnt at level 58",
        "Hammer-arm learnt at level 67"
    ],
    "x-y": [
        "Scratch learnt at level 1",
        "Leer learnt at level 1",
        "Lick learnt at level 1",
        "Fake-tears learnt at level 1",
        "Covet learnt at level 1",
        "Hammer-arm learnt at level 1",
        "Fury-swipes learnt at level 8",
        "Feint-attack learnt at level 15",
        "Sweet-scent learnt at level 22",
        "Play-nice learnt at level 25",
        "Slash learnt at level 29",
        "Scary-face learnt at level 38",
        "Rest learnt at level 47",
        "Snore learnt at level 49",
        "Thrash learnt at level 58",
        "Hammer-arm learnt at level 67"
    ],
    "diamond-pearl": [
        "Scratch learnt at level 1",
        "Leer learnt at level 1",
        "Lick learnt at level 1",
        "Fake-tears learnt at level 1",
        "Covet learnt at level 1",
        "Fury-swipes learnt at level 8",
        "Feint-attack learnt at level 15",
        "Sweet-scent learnt at level 22",
        "Slash learnt at level 29",
        "Scary-face learnt at level 38",
        "Rest learnt at level 47",
        "Snore learnt at level 49",
        "Thrash learnt at level 58",
        "Hammer-arm learnt at level 67"
    ],
    "ruby-sapphire": [
        "Scratch learnt at level 1",
        "Leer learnt at level 1",
        "Lick learnt at level 1",
        "Fury-swipes learnt at level 1",
        "Lick learnt at level 7",
        "Fury-swipes learnt at level 13",
        "Fake-tears learnt at level 19",
        "Feint-attack learnt at level 25",
        "Rest learnt at level 31",
        "Slash learnt at level 37",
        "Snore learnt at level 43",
        "Thrash learnt at level 49"
    ],
    "ultra-sun-ultra-moon": [
        "Scratch learnt at level 1",
        "Leer learnt at level 1",
        "Lick learnt at level 1",
        "Fake-tears learnt at level 1",
        "Covet learnt at level 1",
        "Hammer-arm learnt at level 1",
        "Fury-swipes learnt at level 8",
        "Feint-attack learnt at level 15",
        "Sweet-scent learnt at level 22",
        "Play-nice learnt at level 25",
        "Slash learnt at level 29",
        "Scary-face learnt at level 38",
        "Rest learnt at level 47",
        "Snore learnt at level 49",
        "Thrash learnt at level 58",
        "Hammer-arm learnt at level 67"
    ],
    "sun-moon": [
        "Scratch learnt at level 1",
        "Leer learnt at level 1",
        "Lick learnt at level 1",
        "Fake-tears learnt at level 1",
        "Covet learnt at level 1",
        "Hammer-arm learnt at level 1",
        "Fury-swipes learnt at level 8",
        "Feint-attack learnt at level 15",
        "Sweet-scent learnt at level 22",
        "Play-nice learnt at level 25",
        "Slash learnt at level 29",
        "Scary-face learnt at level 38",
        "Rest learnt at level 47",
        "Snore learnt at level 49",
        "Thrash learnt at level 58",
        "Hammer-arm learnt at level 67"
    ]
}