{
    "black-2-white-2": [
        "Leer learnt at level 1",
        "Double-team learnt at level 1",
        "Powder-snow learnt at level 1",
        "Astonish learnt at level 1",
        "Double-team learnt at level 4",
        "Astonish learnt at level 10",
        "Icy-wind learnt at level 13",
        "Confuse-ray learnt at level 19",
        "Ominous-wind learnt at level 22",
        "Wake-up-slap learnt at level 28",
        "Captivate learnt at level 31",
        "Ice-shard learnt at level 37",
        "Hail learnt at level 40",
        "Blizzard learnt at level 51",
        "Destiny-bond learnt at level 59"
    ],
    "heartgold-soulsilver": [
        "Leer learnt at level 1",
        "Double-team learnt at level 1",
        "Powder-snow learnt at level 1",
        "Astonish learnt at level 1",
        "Double-team learnt at level 4",
        "Astonish learnt at level 10",
        "Icy-wind learnt at level 13",
        "Confuse-ray learnt at level 19",
        "Ominous-wind learnt at level 22",
        "Wake-up-slap learnt at level 28",
        "Captivate learnt at level 31",
        "Ice-shard learnt at level 37",
        "Hail learnt at level 40",
        "Blizzard learnt at level 51",
        "Destiny-bond learnt at level 59"
    ],
    "platinum": [
        "Leer learnt at level 1",
        "Double-team learnt at level 1",
        "Powder-snow learnt at level 1",
        "Astonish learnt at level 1",
        "Double-team learnt at level 4",
        "Astonish learnt at level 10",
        "Icy-wind learnt at level 13",
        "Confuse-ray learnt at level 19",
        "Ominous-wind learnt at level 22",
        "Wake-up-slap learnt at level 28",
        "Captivate learnt at level 31",
        "Ice-shard learnt at level 37",
        "Hail learnt at level 40",
        "Blizzard learnt at level 51",
        "Destiny-bond learnt at level 59"
    ],
    "omega-ruby-alpha-sapphire": [
        "Leer learnt at level 1",
        "Double-team learnt at level 1",
        "Powder-snow learnt at level 1",
        "Destiny-bond learnt at level 1",
        "Ice-shard learnt at level 1",
        "Double-team learnt at level 5",
        "Ice-shard learnt at level 10",
        "Icy-wind learnt at level 14",
        "Astonish learnt at level 19",
        "Draining-kiss learnt at level 23",
        "Ominous-wind learnt at level 28",
        "Confuse-ray learnt at level 32",
        "Wake-up-slap learnt at level 37",
        "Captivate learnt at level 41",
        "Shadow-ball learnt at level 42",
        "Blizzard learnt at level 48",
        "Hail learnt at level 54",
        "Destiny-bond learnt at level 61"
    ],
    "x-y": [
        "Leer learnt at level 1",
        "Double-team learnt at level 1",
        "Powder-snow learnt at level 1",
        "Destiny-bond learnt at level 1",
        "Astonish learnt at level 1",
        "Double-team learnt at level 4",
        "Astonish learnt at level 10",
        "Icy-wind learnt at level 13",
        "Confuse-ray learnt at level 19",
        "Ominous-wind learnt at level 22",
        "Wake-up-slap learnt at level 28",
        "Captivate learnt at level 31",
        "Ice-shard learnt at level 37",
        "Hail learnt at level 40",
        "Blizzard learnt at level 51",
        "Destiny-bond learnt at level 59"
    ],
    "black-white": [
        "Leer learnt at level 1",
        "Double-team learnt at level 1",
        "Powder-snow learnt at level 1",
        "Astonish learnt at level 1",
        "Double-team learnt at level 4",
        "Astonish learnt at level 10",
        "Icy-wind learnt at level 13",
        "Confuse-ray learnt at level 19",
        "Ominous-wind learnt at level 22",
        "Wake-up-slap learnt at level 28",
        "Captivate learnt at level 31",
        "Ice-shard learnt at level 37",
        "Hail learnt at level 40",
        "Blizzard learnt at level 51",
        "Destiny-bond learnt at level 59"
    ],
    "ultra-sun-ultra-moon": [
        "Leer learnt at level 1",
        "Double-team learnt at level 1",
        "Powder-snow learnt at level 1",
        "Destiny-bond learnt at level 1",
        "Ice-shard learnt at level 1",
        "Ominous-wind learnt at level 1",
        "Double-team learnt at level 5",
        "Ice-shard learnt at level 10",
        "Icy-wind learnt at level 14",
        "Astonish learnt at level 19",
        "Draining-kiss learnt at level 23",
        "Will-o-wisp learnt at level 28",
        "Confuse-ray learnt at level 32",
        "Wake-up-slap learnt at level 37",
        "Captivate learnt at level 41",
        "Shadow-ball learnt at level 42",
        "Blizzard learnt at level 48",
        "Hail learnt at level 54",
        "Destiny-bond learnt at level 61"
    ],
    "sun-moon": [
        "Leer learnt at level 1",
        "Double-team learnt at level 1",
        "Powder-snow learnt at level 1",
        "Destiny-bond learnt at level 1",
        "Ice-shard learnt at level 1",
        "Ominous-wind learnt at level 1",
        "Double-team learnt at level 5",
        "Ice-shard learnt at level 10",
        "Icy-wind learnt at level 14",
        "Astonish learnt at level 19",
        "Draining-kiss learnt at level 23",
        "Will-o-wisp learnt at level 28",
        "Confuse-ray learnt at level 32",
        "Wake-up-slap learnt at level 37",
        "Captivate learnt at level 41",
        "Shadow-ball learnt at level 42",
        "Blizzard learnt at level 48",
        "Hail learnt at level 54",
        "Destiny-bond learnt at level 61"
    ],
    "diamond-pearl": [
        "Leer learnt at level 1",
        "Double-team learnt at level 1",
        "Powder-snow learnt at level 1",
        "Astonish learnt at level 1",
        "Double-team learnt at level 4",
        "Astonish learnt at level 10",
        "Icy-wind learnt at level 13",
        "Confuse-ray learnt at level 19",
        "Ominous-wind learnt at level 22",
        "Wake-up-slap learnt at level 28",
        "Captivate learnt at level 31",
        "Ice-shard learnt at level 37",
        "Hail learnt at level 40",
        "Blizzard learnt at level 51",
        "Destiny-bond learnt at level 59"
    ]
}