{
    "omega-ruby-alpha-sapphire": [
        "Tackle learnt at level 1",
        "Tail-whip learnt at level 1",
        "Ember learnt at level 1",
        "Odor-sleuth learnt at level 1",
        "Tail-whip learnt at level 3",
        "Ember learnt at level 7",
        "Odor-sleuth learnt at level 9",
        "Defense-curl learnt at level 13",
        "Flame-charge learnt at level 15",
        "Arm-thrust learnt at level 17",
        "Smog learnt at level 20",
        "Rollout learnt at level 23",
        "Take-down learnt at level 28",
        "Heat-crash learnt at level 31",
        "Assurance learnt at level 36",
        "Flamethrower learnt at level 39",
        "Head-smash learnt at level 44",
        "Roar learnt at level 47",
        "Flare-blitz learnt at level 52"
    ],
    "black-2-white-2": [
        "Tackle learnt at level 1",
        "Tail-whip learnt at level 1",
        "Ember learnt at level 1",
        "Odor-sleuth learnt at level 1",
        "Tail-whip learnt at level 3",
        "Ember learnt at level 7",
        "Odor-sleuth learnt at level 9",
        "Defense-curl learnt at level 13",
        "Flame-charge learnt at level 15",
        "Arm-thrust learnt at level 17",
        "Smog learnt at level 20",
        "Rollout learnt at level 23",
        "Take-down learnt at level 28",
        "Heat-crash learnt at level 31",
        "Assurance learnt at level 36",
        "Flamethrower learnt at level 39",
        "Head-smash learnt at level 44",
        "Roar learnt at level 47",
        "Flare-blitz learnt at level 52"
    ],
    "sun-moon": [
        "Tackle learnt at level 1",
        "Tail-whip learnt at level 1",
        "Ember learnt at level 1",
        "Arm-thrust learnt at level 1",
        "Odor-sleuth learnt at level 1",
        "Tail-whip learnt at level 3",
        "Ember learnt at level 7",
        "Odor-sleuth learnt at level 9",
        "Defense-curl learnt at level 13",
        "Flame-charge learnt at level 15",
        "Smog learnt at level 20",
        "Rollout learnt at level 23",
        "Take-down learnt at level 28",
        "Heat-crash learnt at level 31",
        "Assurance learnt at level 36",
        "Flamethrower learnt at level 39",
        "Head-smash learnt at level 44",
        "Roar learnt at level 47",
        "Flare-blitz learnt at level 52"
    ],
    "x-y": [
        "Tackle learnt at level 1",
        "Tail-whip learnt at level 1",
        "Ember learnt at level 1",
        "Odor-sleuth learnt at level 1",
        "Tail-whip learnt at level 3",
        "Ember learnt at level 7",
        "Odor-sleuth learnt at level 9",
        "Defense-curl learnt at level 13",
        "Flame-charge learnt at level 15",
        "Arm-thrust learnt at level 17",
        "Smog learnt at level 20",
        "Rollout learnt at level 23",
        "Take-down learnt at level 28",
        "Heat-crash learnt at level 31",
        "Assurance learnt at level 36",
        "Flamethrower learnt at level 39",
        "Head-smash learnt at level 44",
        "Roar learnt at level 47",
        "Flare-blitz learnt at level 52"
    ],
    "ultra-sun-ultra-moon": [
        "Tackle learnt at level 1",
        "Tail-whip learnt at level 1",
        "Ember learnt at level 1",
        "Arm-thrust learnt at level 1",
        "Odor-sleuth learnt at level 1",
        "Tail-whip learnt at level 3",
        "Ember learnt at level 7",
        "Odor-sleuth learnt at level 9",
        "Defense-curl learnt at level 13",
        "Flame-charge learnt at level 15",
        "Smog learnt at level 20",
        "Rollout learnt at level 23",
        "Take-down learnt at level 28",
        "Heat-crash learnt at level 31",
        "Assurance learnt at level 36",
        "Flamethrower learnt at level 39",
        "Head-smash learnt at level 44",
        "Roar learnt at level 47",
        "Flare-blitz learnt at level 52"
    ],
    "black-white": [
        "Tackle learnt at level 1",
        "Tail-whip learnt at level 1",
        "Ember learnt at level 1",
        "Odor-sleuth learnt at level 1",
        "Tail-whip learnt at level 3",
        "Ember learnt at level 7",
        "Odor-sleuth learnt at level 9",
        "Defense-curl learnt at level 13",
        "Flame-charge learnt at level 15",
        "Arm-thrust learnt at level 17",
        "Smog learnt at level 20",
        "Rollout learnt at level 23",
        "Take-down learnt at level 28",
        "Heat-crash learnt at level 31",
        "Assurance learnt at level 36",
        "Flamethrower learnt at level 39",
        "Head-smash learnt at level 44",
        "Roar learnt at level 47",
        "Flare-blitz learnt at level 52"
    ]
}